neuraltrust/__init__.py
neuraltrust/api_client/README.md
neuraltrust/api_client/__init__.py
neuraltrust/api_client/client.py
neuraltrust/api_client/core/__init__.py
neuraltrust/api_client/core/api_error.py
neuraltrust/api_client/core/client_wrapper.py
neuraltrust/api_client/core/datetime_utils.py
neuraltrust/api_client/core/file.py
neuraltrust/api_client/core/http_client.py
neuraltrust/api_client/core/jsonable_encoder.py
neuraltrust/api_client/core/pydantic_utilities.py
neuraltrust/api_client/core/query_encoder.py
neuraltrust/api_client/core/remove_none_from_dict.py
neuraltrust/api_client/core/request_options.py
neuraltrust/api_client/environment.py
neuraltrust/api_client/errors/__init__.py
neuraltrust/api_client/errors/method_not_allowed_error.py
neuraltrust/api_client/reference.md
neuraltrust/api_client/tests/utils/test_http_client.py
neuraltrust/api_client/tests/utils/test_query_encoding.py
neuraltrust/api_client/types/__init__.py
neuraltrust/api_client/types/metadata.py
neuraltrust/api_client/types/metadata_browser.py
neuraltrust/api_client/types/metadata_device.py
neuraltrust/api_client/types/metadata_os.py
neuraltrust/api_client/types/trace_response.py
neuraltrust/api_client/types/trace_task.py
neuraltrust/api_client/types/user.py
neuraltrust/api_keys/__init__.py
neuraltrust/api_keys/neuraltrust_api_key.py
neuraltrust/api_keys/openai_api_key.py
neuraltrust/base_evaluator.py
neuraltrust/client.py
neuraltrust/database.py
neuraltrust/errors/__init__.py
neuraltrust/errors/exceptions.py
neuraltrust/eval_type.py
neuraltrust/evaluation_set.py
neuraltrust/evaluator.py
neuraltrust/evaluators/__init__.py
neuraltrust/evaluators/abstract_llm_service.py
neuraltrust/evaluators/correctness/__init__.py
neuraltrust/evaluators/correctness/evaluator.py
neuraltrust/evaluators/correctness/prompt.py
neuraltrust/evaluators/example.py
neuraltrust/evaluators/llm_evaluator.py
neuraltrust/evaluators/openai_service.py
neuraltrust/examples/example_sdk.py
neuraltrust/fern/fern.config.json
neuraltrust_py-0.2.13.dist-info/METADATA
neuraltrust_py-0.2.13.dist-info/WHEEL
neuraltrust_py-0.2.13.dist-info/RECORD
